torchcommon/__init__.py
torchcommon/config.py
torchcommon/models/__init__.py
torchcommon/models/adapters.py
torchcommon/models/cifar/__init__.py
torchcommon/models/cifar/densenet.py
torchcommon/models/cifar/efficientnet.py
torchcommon/models/cifar/resnet.py
torchcommon/models/cifar/vgg.py
torchcommon/models/imagenet/__init__.py
torchcommon/models/imagenet/resnet.py
torchcommon/nn/__init__.py
torchcommon/nn/angular_margin.py
torchcommon/nn/attention.py
torchcommon/nn/functional.py
torchcommon/nn/loss.py
torchcommon/nn/normalization.py
torchcommon/nn/vision.py
torchcommon/optim/__init__.py
torchcommon/optim/adambelief.py
torchcommon/optim/adamx.py
torchcommon/optim/rmsprop.py
torchcommon/optim/scheduler.py
torchcommon/utils/__init__.py
torchcommon/utils/bbox.py
torchcommon/utils/ema.py
torchcommon/utils/image.py
torchcommon/utils/mask.py
torchcommon/utils/metrics/__init__.py
torchcommon/utils/metrics/cls.py
torchcommon/utils/metrics/objdet.py
torchcommon/utils/metrics/semseg.py
torchcommon-0.7.9.dist-info/LICENSE
torchcommon-0.7.9.dist-info/METADATA
torchcommon-0.7.9.dist-info/WHEEL
torchcommon-0.7.9.dist-info/top_level.txt
torchcommon-0.7.9.dist-info/zip-safe
torchcommon-0.7.9.dist-info/RECORD
