Metadata-Version: 2.1
Name: torchcommon
Version: 0.7.9
Summary: Pytorch common utilities.
Home-page: https://github.com/XoriieInpottn/torchcommon
Author: xi
Author-email: gylv@mail.ustc.edu.cn
License: LGPL-2.1 License
Keywords: pytorch,utilities
Platform: any
Classifier: Programming Language :: Python :: 3.8
Classifier: Programming Language :: Python :: 3.9
Classifier: Programming Language :: Python :: 3.10
License-File: LICENSE
Requires-Dist: torch
Requires-Dist: numpy
Requires-Dist: imgaug
Requires-Dist: opencv-python
Requires-Dist: sklearn
Requires-Dist: docset
